trytond/modules/account_de_skr03/__init__.py
trytond/modules/account_de_skr03/account.py
trytond/modules/account_de_skr03/account.xml
trytond/modules/account_de_skr03/account_de.xml
trytond/modules/account_de_skr03/tax_de.xml
trytond/modules/account_de_skr03/tryton.cfg
trytond/modules/account_de_skr03/tests/__init__.py
trytond/modules/account_de_skr03/tests/test_module.py
trytond/modules/account_de_skr03/view/account_type_form.xml
m9s_account_de_skr03-7.0.1.1.dist-info/LICENSE
m9s_account_de_skr03-7.0.1.1.dist-info/METADATA
m9s_account_de_skr03-7.0.1.1.dist-info/WHEEL
m9s_account_de_skr03-7.0.1.1.dist-info/entry_points.txt
m9s_account_de_skr03-7.0.1.1.dist-info/top_level.txt
m9s_account_de_skr03-7.0.1.1.dist-info/RECORD
