Metadata-Version: 2.1
Name: m9s-account-de-skr03
Version: 7.0.1.1
Summary: Tryton Account De Skr03 Module
Home-page: https://www.m9s.biz/
Download-URL: https://gitlab.com/m9s/account_de_skr03.git
Author: MBSolutions
Author-email: info@m9s.biz
License: GPL-3
Project-URL: Bug Tracker, https://support.m9s.biz/
Project-URL: Source Code, https://gitlab.com/m9s/account_de_skr03.git
Classifier: Development Status :: 5 - Production/Stable
Classifier: Environment :: Plugins
Classifier: Framework :: Tryton
Classifier: Intended Audience :: Developers
Classifier: Intended Audience :: Financial and Insurance Industry
Classifier: Intended Audience :: Legal Industry
Classifier: License :: OSI Approved :: GNU General Public License v3 or later (GPLv3+)
Classifier: Natural Language :: Bulgarian
Classifier: Natural Language :: Catalan
Classifier: Natural Language :: Chinese (Simplified)
Classifier: Natural Language :: Czech
Classifier: Natural Language :: Dutch
Classifier: Natural Language :: English
Classifier: Natural Language :: Finnish
Classifier: Natural Language :: French
Classifier: Natural Language :: German
Classifier: Natural Language :: Hungarian
Classifier: Natural Language :: Indonesian
Classifier: Natural Language :: Italian
Classifier: Natural Language :: Persian
Classifier: Natural Language :: Polish
Classifier: Natural Language :: Portuguese (Brazilian)
Classifier: Natural Language :: Romanian
Classifier: Natural Language :: Russian
Classifier: Natural Language :: Slovenian
Classifier: Natural Language :: Spanish
Classifier: Natural Language :: Turkish
Classifier: Natural Language :: Ukrainian
Classifier: Operating System :: OS Independent
Classifier: Programming Language :: Python :: 3
Classifier: Programming Language :: Python :: 3.8
Classifier: Programming Language :: Python :: 3.9
Classifier: Programming Language :: Python :: 3.10
Classifier: Programming Language :: Python :: 3.11
Classifier: Programming Language :: Python :: 3.12
Classifier: Programming Language :: Python :: Implementation :: CPython
Classifier: Topic :: Office/Business
Requires-Python: >=3.8
License-File: LICENSE
Requires-Dist: m9s-trytond <7.1,>=7.0
Requires-Dist: m9s-account-tax-recapitulative-statement <7.1,>=7.0
Requires-Dist: m9s-account-tax-reverse-charge <7.1,>=7.0
Requires-Dist: trytond-account <7.1,>=7.0
Requires-Dist: trytond-account-eu <7.1,>=7.0
Provides-Extra: test
Requires-Dist: m9s-account-deposit <7.1,>=7.0 ; extra == 'test'
